{"name":"Okareader","tagline":"PC,スマホ対応ブラウザRSSリーダー","body":"okareader\r\n=========\r\n\r\n![スクリーンショット](https://raw.github.com/yokano/okareader/master/okareader_ss.png)\r\n\r\nPC,スマホ対応RSSリーダーのWebアプリ  \r\nGoogle App Engine + Go で開発しました  \r\nMitLicense です  \r\nGoogle Reader の xml ファイルをインポートすることも出来ます  \r\nユーザ認証に Google アカウントを使用しています  \r\n\r\n\tokareader/\r\n\t├── LICENSE.txt\r\n\t├── README.md\r\n\t├── app.yaml\r\n\t├── client\r\n\t│   ├── feed.js\r\n\t│   ├── feed.png\r\n\t│   ├── folder.js\r\n\t│   ├── folder.png\r\n\t│   ├── import.js\r\n\t│   ├── okareader.css\r\n\t│   └── okareader.png\r\n\t├── cron.yaml\r\n\t└── server\r\n\t\t├── atom.go\r\n\t\t├── controller.go\r\n\t\t├── html\r\n\t\t│   ├── feed.html\r\n\t\t│   ├── folder.html\r\n\t\t│   ├── import.html\r\n\t\t│   └── login.html\r\n\t\t├── lib.go\r\n\t\t├── main.go\r\n\t\t├── model.go\r\n\t\t├── rss1.go\r\n\t\t├── rss2.go\r\n\t\t└── view.go\r\n\r\n基本的にMVCパターンになっています。  \r\n外部ライブラリとして jQueryMobile を使用しています。\r\n\r\n## 設定ファイル\r\n* app.yaml　　アプリの設定\r\n* cron.yaml　　フィードの定期的な自動更新の設定\r\n\r\n## client/\r\nこのディレクトリはstatic_dirとして設定されています  \r\nhtmlファイルから参照するスクリプトや画像を保存するディレクトリです  \r\ngoから直接このファイルを参照することはできません\r\n\r\n## server/\r\n* main.go　　controllerの呼び出し\r\n* controller.go　　クライアントからのリクエストをViewやModelに振り分けながら処理する\r\n* model.go　　データ操作全般を行う\r\n* view.go　　画面表示全般を行う\r\n* rss1.go　　RSS1.0を読み込むための処理\r\n* rss2.go　　RSS2.0を読み込むための処理\r\n* atom.go　　Atomを読み込むための処理\r\n* lib.go　　その他の汎用的な関数\r\n\r\n## 連絡先\r\nyuta.okano@gmail.com","google":"","note":"Don't delete this file! It's used internally to help with page regeneration."}